{"title":"Body","body":{"description":"the request to attach a volume","content":{"application/json":{"schema":{"type":"object","properties":{"volume":{"type":"object","properties":{"uri":{"type":"string","description":"Uri of the volume to attach.","nullable":true}},"additionalProperties":false,"title":"Aruba.CmpService.ContainerProvider.Dtos.Resources.Data.AttachVolumeDto"}},"additionalProperties":false,"title":"Aruba.CmpService.ContainerProvider.Dtos.Resources.Data.AttachVolumeKaasRequestDto"}},"text/json":{"schema":{"type":"object","properties":{"volume":{"type":"object","properties":{"uri":{"type":"string","description":"Uri of the volume to attach.","nullable":true}},"additionalProperties":false,"title":"Aruba.CmpService.ContainerProvider.Dtos.Resources.Data.AttachVolumeDto"}},"additionalProperties":false,"title":"Aruba.CmpService.ContainerProvider.Dtos.Resources.Data.AttachVolumeKaasRequestDto"}},"application/*+json":{"schema":{"type":"object","properties":{"volume":{"type":"object","properties":{"uri":{"type":"string","description":"Uri of the volume to attach.","nullable":true}},"additionalProperties":false,"title":"Aruba.CmpService.ContainerProvider.Dtos.Resources.Data.AttachVolumeDto"}},"additionalProperties":false,"title":"Aruba.CmpService.ContainerProvider.Dtos.Resources.Data.AttachVolumeKaasRequestDto"}}}}}